face_comparer/__init__.py
face_comparer/face_comparer.py
face_comparer-2.0.dist-info/LICENSE
face_comparer-2.0.dist-info/METADATA
face_comparer-2.0.dist-info/WHEEL
face_comparer-2.0.dist-info/top_level.txt
face_comparer-2.0.dist-info/RECORD
