Metadata-Version: 2.2
Name: face-comparer
Version: 2.0
Summary: A Python module for face comparison using face_recognition and Base64 conversion.
Author-email: Sharjeel Baig <dr.sharjeel.6@gmail.com>
Project-URL: Homepage, https://github.com/sharjeelbaig/face-comparer
Project-URL: Bug Tracker, https://github.com/sharjeelbaig/face-comparer/issues
Classifier: Programming Language :: Python :: 3
Classifier: License :: OSI Approved :: MIT License
Classifier: Operating System :: OS Independent
License-File: LICENSE
Requires-Dist: face_recognition
Requires-Dist: numpy
Requires-Dist: pillow
